{"v":4,"entries":{"principles-introduction--docs":{"id":"principles-introduction--docs","title":"Principles/Introduction","name":"Docs","importPath":"./src/stories/Introduction.stories.mdx","type":"docs","tags":["mdx","docs"],"storiesImports":[],"standalone":false},"components-buttonprimary--docs":{"id":"components-buttonprimary--docs","title":"Components/ButtonPrimary","name":"Docs","importPath":"./src/components/belo-button-primary/belo-button-primary.stories.ts","type":"docs","tags":["docs"],"storiesImports":[],"standalone":false},"components-buttonprimary--belo-button-primary":{"id":"components-buttonprimary--belo-button-primary","title":"Components/ButtonPrimary","name":"Belo Button Primary","importPath":"./src/components/belo-button-primary/belo-button-primary.stories.ts","tags":["story"],"type":"story"},"components-buttonsecondary--docs":{"id":"components-buttonsecondary--docs","title":"Components/ButtonSecondary","name":"Docs","importPath":"./src/components/belo-button-secondary/belo-button-secondary.stories.ts","type":"docs","tags":["docs"],"storiesImports":[],"standalone":false},"components-buttonsecondary--belo-button-secondary":{"id":"components-buttonsecondary--belo-button-secondary","title":"Components/ButtonSecondary","name":"Belo Button Secondary","importPath":"./src/components/belo-button-secondary/belo-button-secondary.stories.ts","tags":["story"],"type":"story"},"components-caption--docs":{"id":"components-caption--docs","title":"Components/Caption","name":"Docs","importPath":"./src/components/belo-caption/belo-caption.stories.ts","type":"docs","tags":["docs"],"storiesImports":[],"standalone":false},"components-caption--caption":{"id":"components-caption--caption","title":"Components/Caption","name":"Caption","importPath":"./src/components/belo-caption/belo-caption.stories.ts","tags":["story"],"type":"story"},"components-card--docs":{"id":"components-card--docs","title":"Components/Card","name":"Docs","importPath":"./src/components/belo-card/belo-card.stories.ts","type":"docs","tags":["docs"],"storiesImports":[],"standalone":false},"components-card--card":{"id":"components-card--card","title":"Components/Card","name":"Card","importPath":"./src/components/belo-card/belo-card.stories.ts","tags":["story"],"type":"story"},"components-header--docs":{"id":"components-header--docs","title":"Components/Header","name":"Docs","importPath":"./src/components/belo-header/belo-header.stories.ts","type":"docs","tags":["docs"],"storiesImports":[],"standalone":false},"components-header--header":{"id":"components-header--header","title":"Components/Header","name":"Header","importPath":"./src/components/belo-header/belo-header.stories.ts","tags":["story"],"type":"story"},"components-input--docs":{"id":"components-input--docs","title":"Components/Input","name":"Docs","importPath":"./src/components/belo-input/belo-input.stories.ts","type":"docs","tags":["docs"],"storiesImports":[],"standalone":false},"components-input--input":{"id":"components-input--input","title":"Components/Input","name":"Input","importPath":"./src/components/belo-input/belo-input.stories.ts","tags":["story"],"type":"story"},"components-anchor--docs":{"id":"components-anchor--docs","title":"Components/Anchor","name":"Docs","importPath":"./src/components/belo-link/belo-link.stories.ts","type":"docs","tags":["docs"],"storiesImports":[],"standalone":false},"components-anchor--anchor":{"id":"components-anchor--anchor","title":"Components/Anchor","name":"Anchor","importPath":"./src/components/belo-link/belo-link.stories.ts","tags":["story"],"type":"story"},"components-paragraph--docs":{"id":"components-paragraph--docs","title":"Components/Paragraph","name":"Docs","importPath":"./src/components/belo-p/belo-p.stories.ts","type":"docs","tags":["docs"],"storiesImports":[],"standalone":false},"components-paragraph--paragraph":{"id":"components-paragraph--paragraph","title":"Components/Paragraph","name":"Paragraph","importPath":"./src/components/belo-p/belo-p.stories.ts","tags":["story"],"type":"story"},"components-textarea--docs":{"id":"components-textarea--docs","title":"Components/TextArea","name":"Docs","importPath":"./src/components/belo-text-area/belo-text-area.stories.ts","type":"docs","tags":["docs"],"storiesImports":[],"standalone":false},"components-textarea--text-area-default":{"id":"components-textarea--text-area-default","title":"Components/TextArea","name":"Text Area Default","importPath":"./src/components/belo-text-area/belo-text-area.stories.ts","tags":["story"],"type":"story"},"components-textarea--text-area-disabled":{"id":"components-textarea--text-area-disabled","title":"Components/TextArea","name":"Text Area Disabled","importPath":"./src/components/belo-text-area/belo-text-area.stories.ts","tags":["story"],"type":"story"}}}
